galenSDK/SDK.py
galenSDK/__init__.py
galenSDK/enumeration/CollectionMethod.py
galenSDK/enumeration/DataOperator.py
galenSDK/enumeration/DataType.py
galenSDK/enumeration/FieldArea.py
galenSDK/enumeration/FieldType.py
galenSDK/enumeration/Gender.py
galenSDK/enumeration/Role.py
galenSDK/enumeration/Scope.py
galenSDK/enumeration/SortOrder.py
galenSDK/enumeration/Status.py
galenSDK/enumeration/__init__.py
galenSDK/exception/AuthenticationFailureException.py
galenSDK/exception/IllegalArgumentException.py
galenSDK/exception/IllegalAuthorizationException.py
galenSDK/exception/ItemNotFoundException.py
galenSDK/exception/__init__.py
galenSDK/exception/httpHandler.py
galenSDK/model/ContactInfo.py
galenSDK/model/CustomField.py
galenSDK/model/CustomFieldData.py
galenSDK/model/DeviceCriteria.py
galenSDK/model/DeviceData.py
galenSDK/model/DeviceDataRecord.py
galenSDK/model/DeviceDataView.py
galenSDK/model/HelperFunctions.py
galenSDK/model/OwnerFilter.py
galenSDK/model/Page.py
galenSDK/model/PageInfo.py
galenSDK/model/Pageable.py
galenSDK/model/Practice.py
galenSDK/model/Sort.py
galenSDK/model/Supplier.py
galenSDK/model/Tenant.py
galenSDK/model/User.py
galenSDK/model/UserRole.py
galenSDK/model/__init__.py
Galen_SDK-1.0.2.dist-info/LICENSE
Galen_SDK-1.0.2.dist-info/METADATA
Galen_SDK-1.0.2.dist-info/WHEEL
Galen_SDK-1.0.2.dist-info/top_level.txt
Galen_SDK-1.0.2.dist-info/RECORD
