Metadata-Version: 2.1
Name: Galen-SDK
Version: 1.0.2
Summary: Galen Data REST API Python Wrapper
Author: Nathanael Goza
Author-email: support@galendata.com
Classifier: Programming Language :: Python :: 3
Classifier: Programming Language :: Python :: 3.6
Classifier: Programming Language :: Python :: 3.7
Classifier: Programming Language :: Python :: 3.8
Classifier: Programming Language :: Python :: 3.9
Classifier: License :: Other/Proprietary License
Classifier: Operating System :: OS Independent
Requires-Python: >=3.6
License-File: LICENSE
Requires-Dist: requests
Requires-Dist: python-dateutil
Requires-Dist: enum34 ; python_version < "3.4"
